etc/photo-importer.cfg
lib/systemd/system/photo-importer.service
photo_importer/__init__.py
photo_importer/config.py
photo_importer/fileprop.py
photo_importer/fileprop_test.py
photo_importer/importer.py
photo_importer/importer_test.py
photo_importer/log.py
photo_importer/mover.py
photo_importer/rotator.py
photo_importer/run.py
photo_importer/server.py
photo_importer/test.py
photo_importer-1.2.6.data/data/share/photo-importer/web/index.html
photo_importer-1.2.6.data/data/share/photo-importer/web/log.png
photo_importer-1.2.6.data/scripts/photo-importer
photo_importer-1.2.6.data/scripts/photo-importer-server
photo_importer-1.2.6.dist-info/LICENSE
photo_importer-1.2.6.dist-info/METADATA
photo_importer-1.2.6.dist-info/WHEEL
photo_importer-1.2.6.dist-info/top_level.txt
photo_importer-1.2.6.dist-info/RECORD
