Metadata-Version: 2.1
Name: photo-importer
Version: 1.2.6
Summary: Photo importer tool
Home-page: https://github.com/sashacmc/photo-importer
Author: Alexander Bushnev
Author-email: Alexander@Bushnev.pro
License: GNU General Public License v3.0
Classifier: Development Status :: 5 - Production/Stable
Classifier: Operating System :: Microsoft :: Windows
Classifier: Operating System :: POSIX :: Linux
Classifier: Operating System :: MacOS
Classifier: Programming Language :: Python
Classifier: Programming Language :: Python :: 3
Classifier: Programming Language :: Python :: 3.6
Classifier: Programming Language :: Python :: 3.7
Classifier: Programming Language :: Python :: 3.8
Classifier: Programming Language :: Python :: 3.9
Classifier: Programming Language :: Python :: 3.10
Classifier: Programming Language :: Python :: 3.11
Classifier: License :: OSI Approved :: GNU General Public License v3 or later (GPLv3+)
Classifier: Topic :: Scientific/Engineering :: Image Processing
Classifier: Topic :: Multimedia :: Video
Classifier: Topic :: Utilities
License-File: LICENSE
Requires-Dist: PyExifTool
Requires-Dist: progressbar
Requires-Dist: psutil
